qjacklogo
