Metadata-Version: 2.4
Name: qjacklogo
Version: 0.2.7
Summary: Animated terminal logo with Arabic text and rainbow effect.
Author: jamalnggau
Classifier: Programming Language :: Python :: 3
Classifier: License :: OSI Approved :: MIT License
Requires-Python: >=3.6
Requires-Dist: pyfiglet
Requires-Dist: colorama
Dynamic: author
Dynamic: classifier
Dynamic: description
Dynamic: description-content-type
Dynamic: requires-dist
Dynamic: requires-python
Dynamic: summary
